subflow/MT-290A_mask_angpix1p1A_box364X36.mrc
subflow/__init__.py
subflow/__main__.py
subflow/config.json
subflow/run_cryolo.py
subflow/run_csparc.py
subflow/run_display_complexpicks.py
subflow/run_display_mcf.py
subflow/run_display_mics.py
subflow/run_display_mtpicks.py
subflow/run_display_split.py
subflow/run_display_subtract.py
subflow/run_eertotif.py
subflow/run_extract.py
subflow/run_fixstar.py
subflow/run_mcf.py
subflow/run_merge.py
subflow/run_miclink.py
subflow/run_movielink.py
subflow/run_preprocess.py
subflow/run_split.py
subflow/run_subtract.py
subflow/subflow.py
subflow/updategui.py
subflow/Schemes/.DS_Store
subflow/Schemes/prep/.DS_Store
subflow/Schemes/prep/scheme.star
subflow/Schemes/prep/ctffind/job.star
subflow/Schemes/prep/importcoords/job.star
subflow/Schemes/prep/importmovies/job.star
subflow/Schemes/prep/motioncorr/job.star
subflow/Schemes/proc/.DS_Store
subflow/Schemes/proc/extract/job.star
subflow-0.28.dist-info/LICENSE
subflow-0.28.dist-info/METADATA
subflow-0.28.dist-info/WHEEL
subflow-0.28.dist-info/entry_points.txt
subflow-0.28.dist-info/top_level.txt
subflow-0.28.dist-info/RECORD
