Metadata-Version: 2.2
Name: subflow
Version: 0.28
Summary: Pipeline for subtracting filaments from cryo-EM micrographs.
Home-page: http://pypi.python.org/pypi/subflow/
Author: Sami Chaaban
Author-email: chaaban@mrc-lmb.cam.ac.uk
License: MIT
Requires-Python: >=3.9
License-File: LICENSE
Requires-Dist: pandas
Requires-Dist: starparser
Requires-Dist: starfile
Requires-Dist: sv_ttk
Requires-Dist: mrcfile
Requires-Dist: numpy
Requires-Dist: scipy
Requires-Dist: cryosparc-tools~=4.6.0
Dynamic: author
Dynamic: author-email
Dynamic: home-page
Dynamic: license
Dynamic: requires-dist
Dynamic: requires-python
Dynamic: summary
